jug/__init__.py
jug/barrier.py
jug/compound.py
jug/hash.py
jug/io.py
jug/jug.py
jug/jug_version.py
jug/mapreduce.py
jug/options.py
jug/task.py
jug/unsafe.py
jug/utils.py
jug/backends/__init__.py
jug/backends/base.py
jug/backends/dict_store.py
jug/backends/encode.py
jug/backends/file_keepalive_monitor.py
jug/backends/file_store.py
jug/backends/memoize_store.py
jug/backends/redis_store.py
jug/backends/select.py
jug/hooks/__init__.py
jug/hooks/execution.py
jug/hooks/exit_checks.py
jug/hooks/register.py
jug/internal/__init__.py
jug/internal/debugger.py
jug/subcommands/__init__.py
jug/subcommands/check.py
jug/subcommands/cleanup.py
jug/subcommands/count.py
jug/subcommands/demo.py
jug/subcommands/execute.py
jug/subcommands/graph.py
jug/subcommands/internal_validation.py
jug/subcommands/invalidate.py
jug/subcommands/pack.py
jug/subcommands/shell.py
jug/subcommands/status.py
jug/subcommands/webstatus.py
jug/tests/__init__.py
jug/tests/task_reset.py
jug/tests/test_barrier.py
jug/tests/test_compound.py
jug/tests/test_encode.py
jug/tests/test_file_store.py
jug/tests/test_hash.py
jug/tests/test_hooks.py
jug/tests/test_io.py
jug/tests/test_jug_check.py
jug/tests/test_jug_execute.py
jug/tests/test_jug_invalidate.py
jug/tests/test_lock.py
jug/tests/test_mapreduce.py
jug/tests/test_no_load.py
jug/tests/test_options.py
jug/tests/test_status.py
jug/tests/test_store.py
jug/tests/test_subcommand_api.py
jug/tests/test_sys_argv.py
jug/tests/test_tasklet.py
jug/tests/test_tasks.py
jug/tests/test_utils_customhash.py
jug/tests/test_utils_identity.py
jug/tests/test_utils_timed_path.py
jug/tests/test_webstatus.py
jug/tests/utils.py
jug/tests/jugfiles/__init__.py
jug/tests/jugfiles/barrier_mapreduce.py
jug/tests/jugfiles/barrier_recurse.py
jug/tests/jugfiles/block_access.py
jug/tests/jugfiles/builtin_function.py
jug/tests/jugfiles/bvalue.py
jug/tests/jugfiles/compound.py
jug/tests/jugfiles/compound_nonsimple.py
jug/tests/jugfiles/compound_wbarrier.py
jug/tests/jugfiles/custom_hash_function.py
jug-2.4.0.dist-info/licenses/COPYING.MIT
jug-2.4.0.dist-info/METADATA
jug-2.4.0.dist-info/WHEEL
jug-2.4.0.dist-info/entry_points.txt
jug-2.4.0.dist-info/top_level.txt
jug-2.4.0.dist-info/RECORD
