Metadata-Version: 2.4
Name: Jug
Version: 2.4.0
Summary: A Task Based Parallelization Framework
Author-email: Luis Pedro Coelho <luis@luispedro.org>
License: MIT
Project-URL: Homepage, https://jug.readthedocs.io
Classifier: Development Status :: 5 - Production/Stable
Classifier: Environment :: Console
Classifier: Operating System :: POSIX
Classifier: Operating System :: OS Independent
Classifier: Programming Language :: Python
Classifier: Programming Language :: Python :: 3
Classifier: Programming Language :: Python :: 3.7
Classifier: Programming Language :: Python :: 3.8
Classifier: Programming Language :: Python :: 3.9
Classifier: Programming Language :: Python :: 3.10
Classifier: Programming Language :: Python :: 3.11
Classifier: Programming Language :: Python :: 3.12
Classifier: Programming Language :: Python :: 3.13
Classifier: Topic :: Scientific/Engineering
Classifier: Topic :: Software Development
Classifier: Topic :: System :: Distributed Computing
Classifier: Intended Audience :: Science/Research
Requires-Python: >=3.7
License-File: COPYING.MIT
Provides-Extra: dev
Requires-Dist: pytest; extra == "dev"
Requires-Dist: numpy; extra == "dev"
Requires-Dist: pyyaml; extra == "dev"
Requires-Dist: redis; extra == "dev"
Dynamic: license-file
